[{"id":1,"first_name":"Nils","last_name":"Martindale","email":"nmartindale0@github.com","gender":"Non-binary"},
{"id":2,"first_name":"Evy","last_name":"Frizzell","email":"efrizzell1@addthis.com","gender":"Female"},
{"id":3,"first_name":"Johnathon","last_name":"Haberfield","email":"jhaberfield2@discovery.com","gender":"Male"},
{"id":4,"first_name":"Ynes","last_name":"Hynes","email":"yhynes3@psu.edu","gender":"Genderfluid"},
{"id":5,"first_name":"Clare","last_name":"Potteridge","email":"cpotteridge4@vinaora.com","gender":"Male"},
{"id":6,"first_name":"Lauralee","last_name":"Christal","email":"lchristal5@cnet.com","gender":"Female"},
{"id":7,"first_name":"Ricky","last_name":"Murie","email":"rmurie6@cbsnews.com","gender":"Genderfluid"},
{"id":8,"first_name":"Maryjane","last_name":"Heustice","email":"mheustice7@yahoo.co.jp","gender":"Polygender"},
{"id":9,"first_name":"Orran","last_name":"Igglesden","email":"oigglesden8@hc360.com","gender":"Male"},
{"id":10,"first_name":"Vladimir","last_name":"Black","email":"vblack9@noaa.gov","gender":"Male"},
{"id":11,"first_name":"Karina","last_name":"Rivlin","email":"krivlina@mashable.com","gender":"Female"},
{"id":12,"first_name":"Eugenio","last_name":"Piecha","email":"epiechab@earthlink.net","gender":"Male"},
{"id":13,"first_name":"Vince","last_name":"Runcieman","email":"vrunciemanc@livejournal.com","gender":"Male"},
{"id":14,"first_name":"Ciro","last_name":"McPeck","email":"cmcpeckd@vistaprint.com","gender":"Male"},
{"id":15,"first_name":"Hannis","last_name":"Barnhart","email":"hbarnharte@berkeley.edu","gender":"Polygender"},
{"id":16,"first_name":"Tam","last_name":"Dayley","email":"tdayleyf@opera.com","gender":"Male"},
{"id":17,"first_name":"Cassi","last_name":"Bonn","email":"cbonng@answers.com","gender":"Female"},
{"id":18,"first_name":"Gussie","last_name":"Maplethorp","email":"gmaplethorph@bbc.co.uk","gender":"Polygender"},
{"id":19,"first_name":"Diann","last_name":"Elwin","email":"delwini@eventbrite.com","gender":"Female"},
{"id":20,"first_name":"Wilden","last_name":"Rickersy","email":"wrickersyj@woothemes.com","gender":"Male"},
{"id":21,"first_name":"Wallache","last_name":"O'Hollegan","email":"wohollegank@marriott.com","gender":"Male"},
{"id":22,"first_name":"Judas","last_name":"Spick","email":"jspickl@webmd.com","gender":"Male"},
{"id":23,"first_name":"Joscelin","last_name":"Spleving","email":"jsplevingm@dion.ne.jp","gender":"Female"},
{"id":24,"first_name":"Adiana","last_name":"Prentice","email":"aprenticen@engadget.com","gender":"Female"},
{"id":25,"first_name":"Sadella","last_name":"Lichfield","email":"slichfieldo@usda.gov","gender":"Female"},
{"id":26,"first_name":"Timmie","last_name":"Saur","email":"tsaurp@si.edu","gender":"Male"},
{"id":27,"first_name":"Cordi","last_name":"Bresner","email":"cbresnerq@google.com.au","gender":"Female"},
{"id":28,"first_name":"Milissent","last_name":"Matresse","email":"mmatresser@google.co.jp","gender":"Female"},
{"id":29,"first_name":"Nestor","last_name":"Pavese","email":"npaveses@skype.com","gender":"Male"},
{"id":30,"first_name":"Kort","last_name":"Lindhe","email":"klindhet@privacy.gov.au","gender":"Male"},
{"id":31,"first_name":"Harv","last_name":"Leisk","email":"hleisku@salon.com","gender":"Male"},
{"id":32,"first_name":"Alberto","last_name":"Hulland","email":"ahullandv@stumbleupon.com","gender":"Male"},
{"id":33,"first_name":"Denney","last_name":"Randal","email":"drandalw@ed.gov","gender":"Male"},
{"id":34,"first_name":"Jelene","last_name":"Malpass","email":"jmalpassx@unblog.fr","gender":"Agender"},
{"id":35,"first_name":"Cathy","last_name":"Ghion","email":"cghiony@icio.us","gender":"Genderfluid"},
{"id":36,"first_name":"Stewart","last_name":"Candy","email":"scandyz@yahoo.co.jp","gender":"Male"},
{"id":37,"first_name":"Rodolph","last_name":"Hannaford","email":"rhannaford10@hostgator.com","gender":"Male"},
{"id":38,"first_name":"Johann","last_name":"Haxell","email":"jhaxell11@blog.com","gender":"Male"},
{"id":39,"first_name":"Gayler","last_name":"Thairs","email":"gthairs12@exblog.jp","gender":"Male"},
{"id":40,"first_name":"Emanuel","last_name":"Larking","email":"elarking13@who.int","gender":"Male"},
{"id":41,"first_name":"Lilas","last_name":"Saffran","email":"lsaffran14@dedecms.com","gender":"Female"},
{"id":42,"first_name":"Nedda","last_name":"Fishley","email":"nfishley15@nbcnews.com","gender":"Female"},
{"id":43,"first_name":"Mattias","last_name":"Halsho","email":"mhalsho16@amazon.de","gender":"Male"},
{"id":44,"first_name":"Madelena","last_name":"Lummis","email":"mlummis17@google.co.uk","gender":"Female"},
{"id":45,"first_name":"Winna","last_name":"Kearle","email":"wkearle18@nydailynews.com","gender":"Female"},
{"id":46,"first_name":"Jemima","last_name":"McCrainor","email":"jmccrainor19@columbia.edu","gender":"Female"},
{"id":47,"first_name":"Elyssa","last_name":"Branton","email":"ebranton1a@epa.gov","gender":"Female"},
{"id":48,"first_name":"Ketti","last_name":"Kewish","email":"kkewish1b@statcounter.com","gender":"Female"},
{"id":49,"first_name":"Piggy","last_name":"Glassford","email":"pglassford1c@whitehouse.gov","gender":"Male"},
{"id":50,"first_name":"Isa","last_name":"Dabling","email":"idabling1d@hhs.gov","gender":"Female"}]